inpaint-0.1.7.dist-info/METADATA
inpaint-0.1.7.dist-info/WHEEL
inpaint-0.1.7.dist-info/licenses/LICENSE
inpaint/__init__.py
inpaint/inpaint.cpython-312-arm-linux-gnueabihf.so
inpaint-0.1.7.dist-info/RECORD
