Metadata-Version: 2.4
Name: inpaint
Version: 0.1.7
Classifier: License :: OSI Approved :: European Union Public Licence 1.2 (EUPL 1.2)
Classifier: Operating System :: POSIX :: Linux
Classifier: Operating System :: MacOS
Classifier: Operating System :: Microsoft :: Windows
Classifier: Programming Language :: Rust
Classifier: Programming Language :: Python :: Implementation :: CPython
Classifier: Programming Language :: Python :: Implementation :: PyPy
Classifier: Programming Language :: Python :: 3
Classifier: Programming Language :: Python :: 3.9
Classifier: Programming Language :: Python :: 3.10
Classifier: Programming Language :: Python :: 3.11
Classifier: Programming Language :: Python :: 3.12
Classifier: Programming Language :: Python :: 3.13
Classifier: Programming Language :: Python :: 3.14
Classifier: Topic :: Scientific/Engineering :: Image Processing
Classifier: Topic :: Multimedia :: Graphics
Requires-Dist: numpy>=1.16.0
Requires-Dist: pillow>=10.0.0
License-File: LICENSE
Summary: Easy to use library for inpainting images.
Author-email: Gilles Vink <gillesvink@noreply.codeberg.org>
Maintainer-email: Gilles Vink <gillesvink@noreply.codeberg.org>
License-Expression: EUPL-1.2
Requires-Python: >=3.9
Project-URL: Homepage, https://codeberg.org/gillesvink/inpaint
Project-URL: Bug Tracker, https://codeberg.org/gillesvink/inpaint/issues
Project-URL: Changelog, https://codeberg.org/gillesvink/inpaint/src/branch/main/CHANGELOG.md
